vxquant/__init__.py
vxquant/__main__.py
vxquant/_tdgateway.py
vxquant/eventbroker.py
vxquant/exceptions.py
vxquant/executeunit.py
vxquant/mdapi/__init__.py
vxquant/mdapi/base.py
vxquant/mdapi/hq/__init__.py
vxquant/mdapi/hq/tdx.py
vxquant/mdapi/hq/tencent.py
vxquant/model/__init__.py
vxquant/model/contants.py
vxquant/model/exchange.py
vxquant/model/portfolio.py
vxquant/model/preset.py
vxquant/model/tools/__init__.py
vxquant/model/tools/gmData.py
vxquant/model/tools/tdxData.py
vxquant/scripts/__init__.py
vxquant/scripts/backtest.py
vxquant/scripts/datacollector.py
vxquant/scripts/eventbroker.py
vxquant/scripts/gmagent.py
vxquant/scripts/tdgateway.py
vxquant/simagent.py
vxquant/strategy/datacollector.py
vxquant/strategy/executeunit.py
vxquant/strategy/pms_events.py
vxquant/strategy/pms_system.py
vxquant/strategy/system.py
vxquant/tdapi/__init__.py
vxquant/tdapi/base.py
vxquant/tdapi/gm.py
vxquant/tdapi/gmtrade.py
vxquant/tdapi/sim.py
vxsched/__init__.py
vxsched/__main__.py
vxsched/broker.py
vxsched/context.py
vxsched/core.py
vxsched/event.py
vxsched/pubsubs/__init__.py
vxsched/pubsubs/ftp.py
vxsched/pubsubs/zeromq.py
vxsched/rpc.py
vxsched/scripts/__init__.py
vxsched/scripts/backtest.py
vxsched/scripts/living.py
vxsched/scripts/shmserver.py
vxsched/scripts/zmqserver.py
vxsched/triggers/__init__.py
vxsched/triggers/daily.py
vxsched/triggers/interval.py
vxsched/triggers/once.py
vxsched/triggers/weekly.py
vxutils/__init__.py
vxutils/cache.py
vxutils/convertors.py
vxutils/database/__init__.py
vxutils/database/mongodb.py
vxutils/database/monogo.py
vxutils/database/sqlite.py
vxutils/dataclass.py
vxutils/decorators.py
vxutils/exceptions.py
vxutils/log.py
vxutils/net.py
vxutils/timer.py
vxutils/toolbox.py
vxutils/zmqsocket.py
vxquantlib-2022.9.28.dist-info/LICENSE
vxquantlib-2022.9.28.dist-info/WHEEL
vxquantlib-2022.9.28.dist-info/METADATA
vxquantlib-2022.9.28.dist-info/RECORD
