Metadata-Version: 2.1
Name: vxquantlib
Version: 2022.9.28
Summary: 基于事件驱动的量化交易基础框架
Home-page: https://gitee.com/vxquantlib/vxquantlib
License: MIT
Keywords: quant,tools
Author: vex1023
Author-email: vex1023@qq.com
Requires-Python: >=3.7,<4.0
Classifier: License :: OSI Approved :: MIT License
Classifier: Programming Language :: Python
Classifier: Programming Language :: Python :: 3
Classifier: Programming Language :: Python :: 3.7
Classifier: Programming Language :: Python :: 3.8
Classifier: Programming Language :: Python :: 3.9
Classifier: Programming Language :: Python :: 3.10
Classifier: Programming Language :: Python :: 3
Classifier: Programming Language :: Python :: 3.10
Classifier: Programming Language :: Python :: 3.11
Classifier: Programming Language :: Python :: 3.7
Classifier: Programming Language :: Python :: 3.8
Classifier: Programming Language :: Python :: 3.9
Classifier: Programming Language :: Python :: Implementation :: CPython
Classifier: Programming Language :: Python :: Implementation :: PyPy
Requires-Dist: pymongo
Requires-Dist: python-dateutil
Requires-Dist: pyzmq
Requires-Dist: requests
Requires-Dist: six
